zeroae/goblet/__init__.py
zeroae/goblet/__main__.py
zeroae/goblet/_version.py
zeroae/goblet/cli.py
zeroae/goblet/config.py
zeroae/goblet/utils.py
zeroae/goblet/views.py
zeroae/goblet/chalice/__init__.py
zeroae/goblet/chalice/blueprint.py
zeroae/goblet/templates/setup.jinja2
zeroae_goblet-0.0.1.dist-info/LICENSE
zeroae_goblet-0.0.1.dist-info/METADATA
zeroae_goblet-0.0.1.dist-info/WHEEL
zeroae_goblet-0.0.1.dist-info/entry_points.txt
zeroae_goblet-0.0.1.dist-info/top_level.txt
zeroae_goblet-0.0.1.dist-info/RECORD
