Metadata-Version: 2.1
Name: zeroae-goblet
Version: 0.0.1
Summary: A Chalice blueprint for creating GitHub Apps
Home-page: https://github.com/zeroae/zeroae-goblet
Author: Patrick Sodré
Author-email: psodre@gmail.com
License: Apache
Keywords: goblet zeroae
Platform: UNKNOWN
Classifier: Development Status :: 2 - Pre-Alpha
Classifier: Intended Audience :: Developers
Classifier: License :: OSI Approved :: Apache Software License
Classifier: Natural Language :: English
Classifier: Programming Language :: Python :: 3
Classifier: Programming Language :: Python :: 3.6
Classifier: Programming Language :: Python :: 3.7
Classifier: Programming Language :: Python :: 3.8
Requires-Python: >=3.6
Requires-Dist: chalice (>=1.13)
Requires-Dist: click (>=7.0)
Requires-Dist: click-plugins
Requires-Dist: entrypoints
Requires-Dist: environs
Requires-Dist: jinja2 (<3,>=2.9)
Requires-Dist: octokitpy (<0.14,>=0.13.0)
Requires-Dist: PyPubSub (<5,>=4.0.3)
Requires-Dist: python-dateutil
Provides-Extra: test
Requires-Dist: pytest (>=3) ; extra == 'test'
Requires-Dist: pytest-chalice ; extra == 'test'
Requires-Dist: pytest-cov ; extra == 'test'
